examples/example_decorator.py
examples/example_utils.py
examples/example_wrapper.py
functimer/__init__.py
functimer/__main__.py
functimer/classes.py
functimer/exceptions.py
functimer/functimer.py
functimer/util.py
tests/__init__.py
tests/conftest.py
tests/test_classes.py
tests/test_cli.py
tests/test_functimer.py
tests/test_util.py
functimer-1.3.1.dist-info/LICENSE.md
functimer-1.3.1.dist-info/WHEEL
functimer-1.3.1.dist-info/METADATA
functimer-1.3.1.dist-info/RECORD
