Metadata-Version: 2.1
Name: functimer
Version: 1.3.1
Summary: A programmatic approach to function runtime estimation.
Home-page: https://github.com/EJEmmett/functimer
License: MIT
Keywords: timer,runtime,timing,function,decorator
Author: Edward Emmett
Author-email: edemms12@gmail.com
Maintainer: Edward Emmett
Maintainer-email: edemms12@gmail.com
Requires-Python: >=3.6,<4.0
Classifier: Intended Audience :: Developers
Classifier: License :: OSI Approved :: MIT License
Classifier: Operating System :: OS Independent
Classifier: Programming Language :: Python :: 3
Classifier: Programming Language :: Python :: 3 :: Only
Classifier: Programming Language :: Python :: 3.10
Classifier: Programming Language :: Python :: 3.6
Classifier: Programming Language :: Python :: 3.7
Classifier: Programming Language :: Python :: 3.8
Classifier: Programming Language :: Python :: 3.9
Classifier: Topic :: Software Development :: Libraries :: Python Modules
Provides-Extra: tests
Project-URL: Repository, https://github.com/EJEmmett/functimer.git
